cancerlab/__init__.py
cancerlab_pythonlibrary-1.0.0.dist-info/METADATA
cancerlab_pythonlibrary-1.0.0.dist-info/WHEEL
cancerlab_pythonlibrary-1.0.0.dist-info/top_level.txt
cancerlab_pythonlibrary-1.0.0.dist-info/RECORD
