Metadata-Version: 2.4
Name: cancerlab-pythonlibrary
Version: 1.0.0
Summary: Machine Learning library for cancer detection and analysis
Home-page: https://github.com/balagaraghuram/cancerlab_pythonlibrary
Author: Balaga Raghuram
Author-email: your.email@example.com
Keywords: cancer machine-learning healthcare medical-ai
Classifier: Development Status :: 4 - Beta
Classifier: Intended Audience :: Healthcare Industry
Classifier: Intended Audience :: Science/Research
Classifier: License :: OSI Approved :: MIT License
Classifier: Programming Language :: Python :: 3
Classifier: Programming Language :: Python :: 3.8
Classifier: Programming Language :: Python :: 3.9
Classifier: Programming Language :: Python :: 3.10
Classifier: Programming Language :: Python :: 3.11
Requires-Python: >=3.8
Requires-Dist: numpy>=1.20.0
Requires-Dist: scikit-learn>=1.0.0
Dynamic: author
Dynamic: author-email
Dynamic: classifier
Dynamic: description
Dynamic: description-content-type
Dynamic: home-page
Dynamic: keywords
Dynamic: requires-dist
Dynamic: requires-python
Dynamic: summary
